MANIFEST.in
README.rst
setup.cfg
setup.py
odesk/__init__.py
odesk/client.py
odesk/config.py
odesk/exceptions.py
odesk/http.py
odesk/namespaces.py
odesk/oauth.py
odesk/tests.py
odesk/utils.py
odesk/routers/__init__.py
odesk/routers/finreport.py
odesk/routers/hr.py
odesk/routers/job.py
odesk/routers/mc.py
odesk/routers/offers.py
odesk/routers/provider.py
odesk/routers/task.py
odesk/routers/team.py
odesk/routers/timereport.py
python_odesk.egg-info/PKG-INFO
python_odesk.egg-info/SOURCES.txt
python_odesk.egg-info/dependency_links.txt
python_odesk.egg-info/requires.txt
python_odesk.egg-info/top_level.txt