Metadata-Version: 1.1
Name: python-odesk
Version: 0.5.8
Summary: Python bindings to oDesk API
Home-page: http://odesk.github.com/python-odesk
Author: Kirill Panshin
Author-email: kamelok@odesk.com
License: BSD
Download-URL: http://github.com/odesk/python-odesk
Platform: UNKNOWN
Classifier: Development Status :: 5 - Production/Stable
Classifier: Environment :: Web Environment
Classifier: Intended Audience :: Developers
Classifier: License :: OSI Approved :: BSD License
Classifier: Operating System :: OS Independent
Classifier: Programming Language :: Python
Classifier: Topic :: Software Development :: Libraries :: Python Modules
Classifier: Topic :: Utilities
